polibraslogin/__init__.py
polibraslogin/admin.py
polibraslogin/apps.py
polibraslogin/models.py
polibraslogin/social.py
polibraslogin/tests.py
polibraslogin/views.py
polibraslogin/migrations/__init__.py
polibraslogin/templates/admin/base.html
polibraslogin/templates/admin/login.html
django_polibras_login-0.1.0.dist-info/LICENSE
django_polibras_login-0.1.0.dist-info/METADATA
django_polibras_login-0.1.0.dist-info/WHEEL
django_polibras_login-0.1.0.dist-info/top_level.txt
django_polibras_login-0.1.0.dist-info/RECORD
