Metadata-Version: 2.1
Name: django-polibras-login
Version: 0.1.0
Summary: A Django app to realize login with google on polibras environments.
Home-page: https://polibrassoftware.com.br/
Author: Andre Conjo
Author-email: andre.conjo@polibrassoftware.com.br
License: BSD-3-Clause
Platform: UNKNOWN
Classifier: Framework :: Django :: 3.0
Classifier: License :: OSI Approved :: BSD License
Classifier: Programming Language :: Python
Classifier: Programming Language :: Python :: 3
Classifier: Programming Language :: Python :: 3 :: Only
Requires-Python: >=3.6
License-File: LICENSE
Requires-Dist: django-allauth (<1.0.0,>=0.45.0)
Requires-Dist: django-environ
